bawx_player/__init__.py
bawx_player/pycdg.py
bawx_player/pycdgAux.py
bawx_player/pykar.py
bawx_player/pykconstants.py
bawx_player/pykdb.py
bawx_player/pykenv.py
bawx_player/pykmanager.py
bawx_player/pykplayer.py
bawx_player/pykversion.py
bawx_player/pympg.py
bawx_player-0.9.1.dist-info/LICENSE
bawx_player-0.9.1.dist-info/METADATA
bawx_player-0.9.1.dist-info/WHEEL
bawx_player-0.9.1.dist-info/top_level.txt
bawx_player-0.9.1.dist-info/RECORD
